d2py/__init__.py
d2py/timeitx.py
d2py/abc/__init__.py
d2py/abc/profile.py
d2py/abc/trace_code.py
d2py/abc/validate.py
d2py/algebra/__init__.py
d2py/analysis/__init__.py
d2py/download/__init__.py
d2py/drlhp/__init__.py
d2py/gui/__init__.py
d2py/gui/qt/__init__.py
d2py/gui/qt/qt5.py
d2py/gui/qt/qt6.py
d2py/gui/qt/widgets/__init__.py
d2py/gui/qt/widgets/rect.py
d2py/gui/tkinterx/__init__.py
d2py/gui/tkinterx/tips.py
d2py/gui/tkinterx/tooltip.py
d2py/gui/tkinterx/graph/__init__.py
d2py/gui/tkinterx/graph/base.py
d2py/gui/tkinterx/graph/selector.py
d2py/gui/tkinterx/graph/shape.py
d2py/gui/tkinterx/graph/window.py
d2py/quantum/__init__.py
d2py/quantum/graph/__init__.py
d2py/quantum/graph/tree.py
d2py/tasks/__init__.py
d2py/tasks/utils.py
d2py/te/__init__.py
d2py/te/tensor.py
d2py/testing/__init__.py
d2py/tools/__init__.py
d2py/tools/dashstyle/__init__.py
d2py/tools/dashstyle/server.py
d2py/tools/dashstyle/design/__init__.py
d2py/tools/dashstyle/design/template.py
d2py/tools/dashstyle/utils/__init__.py
d2py/tools/dashstyle/utils/nav.py
d2py/tools/sanstyle/__init__.py
d2py/tools/sanstyle/utils.py
d2py/tools/sanstyle/display/__init__.py
d2py/tools/sanstyle/display/_html.py
d2py/tools/sanstyle/display/html.py
d2py/tools/sanstyle/display/template.py
d2py/tools/sanstyle/github/__init__.py
d2py/tools/sanstyle/github/file.py
d2py/tools/write/__init__.py
d2py/tools/write/_docs.py
d2py/tools/write/doc.py
d2py/tools/write/release.py
d2py/utils/__init__.py
d2py/utils/data.py
d2py/utils/file.py
d2py/utils/log_config.py
d2py/utils/unzip.py
d2py-0.7.0.dist-info/LICENSE
d2py-0.7.0.dist-info/WHEEL
d2py-0.7.0.dist-info/METADATA
d2py-0.7.0.dist-info/RECORD
