Metadata-Version: 2.3
Name: d2py
Version: 0.7.0
Summary: Dive into Python.
Author-email: xinetzone <735613050@qq.com>
Maintainer-email: xinetzone <735613050@qq.com>
Requires-Python: >=3.10
Classifier: License :: OSI Approved :: Apache Software License
Requires-Dist: pdm ; extra == "dev"
Requires-Dist: pygame ; extra == "dev"
Requires-Dist: PyGithub[integrations] ; extra == "dev"
Requires-Dist: bytecode ; extra == "dev"
Requires-Dist: numpy ; extra == "dev"
Requires-Dist: toml ; extra == "dev"
Requires-Dist: fsspec ; extra == "dev"
Requires-Dist: pyarrow ; extra == "dev"
Requires-Dist: invoke ; extra == "dev"
Requires-Dist: openpyxl ; extra == "dev"
Requires-Dist: rich[jupyter] ; extra == "dev"
Requires-Dist: grpcio ; extra == "dev"
Requires-Dist: absl-py ; extra == "dev"
Requires-Dist: ping3 ; extra == "dev"
Requires-Dist: paramiko ; extra == "dev"
Requires-Dist: tables ; extra == "dev"
Requires-Dist: myst-nb ; extra == "doc"
Requires-Dist: xyzstyle ; extra == "doc"
Requires-Dist: sphinx-copybutton ; extra == "doc"
Requires-Dist: sphinx-thebe ; extra == "doc"
Requires-Dist: sphinx-design ; extra == "doc"
Requires-Dist: sphinx-automodapi ; extra == "doc"
Requires-Dist: sphinx-sitemap ; extra == "doc"
Requires-Dist: sphinx-comments ; extra == "doc"
Requires-Dist: invoke ; extra == "doc"
Requires-Dist: sphinx-autoapi ; extra == "doc"
Requires-Dist: PySide6 ; extra == "gui"
Project-URL: Home, https://github.com/xinetzone/d2py
Provides-Extra: dev
Provides-Extra: doc
Provides-Extra: gui
